[
    {
      "id": 1,
      "category_id": 1,
      "title": "Smart LED TV",
      "slug": "smart-led-tv",
      "short_description": "Enjoy a smart viewing experience with this LED TV.",
      "detailed_description": "This Smart LED TV offers stunning picture quality and a range of smart features for an immersive entertainment experience.",
      "image": "/images/products/smart-led-tv.jpeg",
      "images": ["tv1_1.jpg", "tv1_2.jpg", "tv1_3.jpg"],
      "isFeatured": true,
      "isTrending": true,
      "brand": "ExampleBrand",
      "keywords": ["Smart TV", "LED TV", "Television", "HD TV"],
      "initialPrice": 799.99,
      "currentPrice": 699.99,
      "ratings": 4.5
    },
    {
      "id": 2,
      "category_id": 1,
      "title": "4K Ultra HD TV",
      "slug": "4k-ultra-hd-tv",
      "short_description": "Experience lifelike visuals with this 4K Ultra HD TV.",
      "detailed_description": "This 4K Ultra HD TV delivers stunning clarity and exceptional color reproduction for a cinematic viewing experience at home.",
      "image": "/images/products/4K-Ultra-HD-TV.jpeg",
      "images": ["tv2_1.jpg", "tv2_2.jpg", "tv2_3.jpg"],
      "isFeatured": false,
      "isTrending": true,
      "brand": "ExampleBrand",
      "keywords": ["4K TV", "Ultra HD TV", "Television", "Smart TV"],
      "initialPrice": 999.99,
      "currentPrice": 899.99,
      "ratings": 4.8
    },
    {
      "id": 3,
      "category_id": 1,
      "title": "OLED Curved TV",
      "slug": "oled-curved-tv",
      "short_description": "Immerse yourself in the beauty of this OLED Curved TV.",
      "detailed_description": "This OLED Curved TV provides an extraordinary visual experience with its curved display and stunning OLED technology.",
      "image": "/images/products/OLED-Curved-TV.jpg",
      "images": ["tv3_1.jpg", "tv3_2.jpg", "tv3_3.jpg"],
      "isFeatured": true,
      "isTrending": false,
      "brand": "ExampleBrand",
      "keywords": ["OLED TV", "Curved TV", "Television", "Smart TV"],
      "initialPrice": 1499.99,
      "currentPrice": 1299.99,
      "ratings": 4.7
    },
    {
        "id": 1,
        "category_id": 2,
        "title": "French Door Fridge",
        "slug": "french-door-fridge",
        "short_description": "Keep your food fresh with this spacious French Door Fridge.",
        "detailed_description": "This French Door Fridge offers ample storage space and advanced cooling technology to preserve your groceries for longer.",
        "image": "/images/products/French-Door-Fridge.jpg",
        "images": ["fridge1_1.jpg", "fridge1_2.jpg", "fridge1_3.jpg"],
        "isFeatured": true,
        "isTrending": true,
        "brand": "ExampleBrand",
        "keywords": ["French Door Fridge", "Refrigerator", "Fridge", "Cooling"],
        "initialPrice": 1299.99,
        "currentPrice": 1199.99,
        "ratings": 4.6
      },
      {
        "id": 2,
        "category_id": 2,
        "title": "Side-by-Side Fridge",
        "slug": "side-by-side-fridge",
        "short_description": "Organize your groceries easily with this convenient Side-by-Side Fridge.",
        "detailed_description": "This Side-by-Side Fridge offers a spacious layout and convenient access to both the fridge and freezer compartments.",
        "image": "/images/products/Side-by-Side-Fridge.jpeg",
        "images": ["fridge2_1.jpg", "fridge2_2.jpg", "fridge2_3.jpg"],
        "isFeatured": false,
        "isTrending": true,
        "brand": "ExampleBrand",
        "keywords": ["Side-by-Side Fridge", "Refrigerator", "Fridge", "Freezer"],
        "initialPrice": 999.99,
        "currentPrice": 899.99,
        "ratings": 4.4
      },
      {
        "id": 3,
        "category_id": 2,
        "title": "Mini Fridge",
        "slug": "mini-fridge",
        "short_description": "Compact and portable, this Mini Fridge is perfect for small spaces.",
        "detailed_description": "This Mini Fridge is energy-efficient and ideal for dorm rooms, offices, or small apartments.",
        "image": "/images/products/Mini-Fridge.jpeg",
        "images": ["fridge3_1.jpg", "fridge3_2.jpg", "fridge3_3.jpg"],
        "isFeatured": true,
        "isTrending": false,
        "brand": "ExampleBrand",
        "keywords": ["Mini Fridge", "Small Fridge", "Compact Refrigerator"],
        "initialPrice": 199.99,
        "currentPrice": 179.99,
        "ratings": 4.2
      },
      {
        "id": 1,
        "category_id": 3,
        "title": "Countertop Microwave",
        "slug": "countertop-microwave",
        "short_description": "Efficient and compact, this Countertop Microwave fits any kitchen.",
        "detailed_description": "This Countertop Microwave offers various cooking options and a space-saving design, making it perfect for small kitchens or dorm rooms.",
        "image": "/images/products/Countertop-Microwave.jpg",
        "images": ["microwave1_1.jpg", "microwave1_2.jpg", "microwave1_3.jpg"],
        "isFeatured": true,
        "isTrending": true,
        "brand": "ExampleBrand",
        "keywords": ["Countertop Microwave", "Microwave Oven", "Cooking Appliance"],
        "initialPrice": 99.99,
        "currentPrice": 89.99,
        "ratings": 4.5
      },
      {
        "id": 2,
        "category_id": 3,
        "title": "Over-the-Range Microwave",
        "slug": "over-the-range-microwave",
        "short_description": "Convenient and powerful, this Over-the-Range Microwave streamlines your kitchen.",
        "detailed_description": "This Over-the-Range Microwave comes with advanced features and provides additional counter space by mounting it above your stove.",
        "image": "/images/products/Over-the-Range-Microwave.jpeg",
        "images": ["microwave2_1.jpg", "microwave2_2.jpg", "microwave2_3.jpg"],
        "isFeatured": false,
        "isTrending": true,
        "brand": "ExampleBrand",
        "keywords": ["Over-the-Range Microwave", "Microwave Oven", "Cooking Appliance"],
        "initialPrice": 249.99,
        "currentPrice": 219.99,
        "ratings": 4.8
      },
      {
        "id": 3,
        "category_id": 3,
        "title": "Convection Microwave",
        "slug": "convection-microwave",
        "short_description": "Enjoy versatile cooking with this Convection Microwave.",
        "detailed_description": "This Convection Microwave combines microwave and convection oven functionality, allowing you to bake, roast, and microwave food with ease.",
        "image": "/images/products/Convection-Microwave.jpeg",
        "images": ["microwave3_1.jpg", "microwave3_2.jpg", "microwave3_3.jpg"],
        "isFeatured": true,
        "isTrending": false,
        "brand": "ExampleBrand",
        "keywords": ["Convection Microwave", "Microwave Oven", "Cooking Appliance"],
        "initialPrice": 179.99,
        "currentPrice": 159.99,
        "ratings": 4.7
      },
      {
        "id": 1,
        "category_id": 4,
        "title": "Front-load Washing Machine",
        "slug": "front-load-washing-machine",
        "short_description": "Efficient and gentle on clothes, this Front-load Washing Machine gets the job done.",
        "detailed_description": "This Front-load Washing Machine offers advanced washing features and a spacious drum to handle large loads with care.",
        "image": "/images/products/Front-load Washing-Machine.png",
        "images": ["laundry1_1.jpg", "laundry1_2.jpg", "laundry1_3.jpg"],
        "isFeatured": true,
        "isTrending": true,
        "brand": "ExampleBrand",
        "keywords": ["Front-load Washing Machine", "Laundry Machine", "Washer"],
        "initialPrice": 799.99,
        "currentPrice": 699.99,
        "ratings": 4.6
      },
      {
        "id": 2,
        "category_id": 4,
        "title": "Top-load Washing Machine",
        "slug": "top-load-washing-machine",
        "short_description": "Convenient and reliable, this Top-load Washing Machine makes laundry a breeze.",
        "detailed_description": "This Top-load Washing Machine features multiple wash programs and a user-friendly design for easy operation.",
        "image": "/images/products/Top-load-Washing-Machine.jpg",
        "images": ["laundry2_1.jpg", "laundry2_2.jpg", "laundry2_3.jpg"],
        "isFeatured": false,
        "isTrending": true,
        "brand": "ExampleBrand",
        "keywords": ["Top-load Washing Machine", "Laundry Machine", "Washer"],
        "initialPrice": 599.99,
        "currentPrice": 549.99,
        "ratings": 4.4
      },
      {
        "id": 3,
        "category_id": 4,
        "title": "Electric Dryer",
        "slug": "electric-dryer",
        "short_description": "Efficiently dry your clothes with this Electric Dryer.",
        "detailed_description": "This Electric Dryer offers multiple drying settings and a large drum capacity to handle your laundry needs.",
        "image": "/images/products/Electric-Dryer.jpeg",
        "images": ["laundry3_1.jpg", "laundry3_2.jpg", "laundry3_3.jpg"],
        "isFeatured": true,
        "isTrending": false,
        "brand": "ExampleBrand",
        "keywords": ["Electric Dryer", "Laundry Machine", "Dryer"],
        "initialPrice": 699.99,
        "currentPrice": 629.99,
        "ratings": 4.7
      }
  ]
  